odoo/addons/web_remember_tree_column_width/README.rst
odoo/addons/web_remember_tree_column_width/__init__.py
odoo/addons/web_remember_tree_column_width/__manifest__.py
odoo/addons/web_remember_tree_column_width/i18n/web_remember_tree_column_width.pot
odoo/addons/web_remember_tree_column_width/readme/CONTRIBUTORS.rst
odoo/addons/web_remember_tree_column_width/readme/CREDITS.rst
odoo/addons/web_remember_tree_column_width/readme/DESCRIPTION.rst
odoo/addons/web_remember_tree_column_width/static/description/icon.png
odoo/addons/web_remember_tree_column_width/static/description/index.html
odoo/addons/web_remember_tree_column_width/static/src/js/list_renderer.js
odoo/addons/web_remember_tree_column_width/static/src/scss/main.scss
odoo/addons/web_remember_tree_column_width/views/assets.xml
odoo14_addon_web_remember_tree_column_width-14.0.1.0.1.dev3.dist-info/METADATA
odoo14_addon_web_remember_tree_column_width-14.0.1.0.1.dev3.dist-info/WHEEL
odoo14_addon_web_remember_tree_column_width-14.0.1.0.1.dev3.dist-info/top_level.txt
odoo14_addon_web_remember_tree_column_width-14.0.1.0.1.dev3.dist-info/RECORD
